LICENSE.txt
MANIFEST.in
README.rst
setup.py
src/pyramid_authstack/__init__.py
src/pyramid_authstack/tests.py
src/pyramid_authstack.egg-info/PKG-INFO
src/pyramid_authstack.egg-info/SOURCES.txt
src/pyramid_authstack.egg-info/dependency_links.txt
src/pyramid_authstack.egg-info/requires.txt
src/pyramid_authstack.egg-info/top_level.txt
src/pyramid_authstack.egg-info/zip-safe