Metadata-Version: 1.1
Name: pyramid-authstack
Version: 1.0.0
Summary: Use multiple authentication policies with pyramid
Home-page: https://github.com/wichert/pyramid_authstack
Author: Simplon B.V. - Wichert Akkerman
Author-email: wichert@wiggy.net
License: BSD
Platform: UNKNOWN
Classifier: Development Status :: 4 - Beta
Classifier: Framework :: Pyramid
Classifier: Intended Audience :: Developers
Classifier: License :: OSI Approved :: MIT License
Classifier: Programming Language :: Python :: 2.7
Classifier: Programming Language :: Python :: 3.2
Classifier: Programming Language :: Python :: 3.3
Classifier: Topic :: Software Development :: Libraries :: Python Modules
